gewe_notice/__init__.py
gewe_notice/main.py
gewe_notice/server.py
gewe_notice-1.0.1.dist-info/METADATA
gewe_notice-1.0.1.dist-info/WHEEL
gewe_notice-1.0.1.dist-info/entry_points.txt
gewe_notice-1.0.1.dist-info/RECORD
