Metadata-Version: 2.4
Name: gewe-notice
Version: 1.0.1
Summary: 一个轻量级的 MCP 服务器，用于通过gewe微信机器人发送 AI 任务状态通知。
Project-URL: Homepage, https://github.com/wangnov/gewe-notice
Project-URL: Repository, https://github.com/wangnov/gewe-notice
Author: wangnov
Keywords: ai,gewe,mcp,notification
Classifier: Development Status :: 4 - Beta
Classifier: Intended Audience :: Developers
Classifier: License :: OSI Approved :: MIT License
Classifier: Programming Language :: Python :: 3
Requires-Python: >=3.10
Requires-Dist: fastmcp>=2.0.0
Requires-Dist: httpx>=0.27.0
Requires-Dist: loguru>=0.7.0
Requires-Dist: typer>=0.12.0
